{
	"status": {
		"max": {
			"attack": 1029,
			"health": 5097,
			"speed": 126,
			"defense": 473,
			"critical_hit": 23,
			"critical_damage": 150,
			"unity_chance": 5,
			"debuff_hit": 0,
			"debuff_resist": 0
		},
		"init": {
			"attack": 501,
			"health": 2844,
			"speed": 120,
			"defense": 297,
			"critical_hit": 15,
			"critical_damage": 150,
			"unity_chance": 5,
			"debuff_hit": 0,
			"debuff_resist": 0
		}
	},
	"stamp": {
		"expansion": [
			{
				"label": "スピード",
				"value": 3,
				"type": "fix"
			},
			{
				"label": "スピード",
				"value": 4,
				"type": "fix"
			},
			{
				"label": "スピード",
				"value": 6,
				"type": "fix"
			},
			{
				"label": "スピード",
				"value": 7,
				"type": "fix"
			},
			{
				"label": "スピード",
				"value": 9,
				"type": "fix"
			},
			{
				"label": "スピード",
				"value": 10,
				"type": "fix"
			}
		],
		"collect": [
			{
				"label": "クリティカル発生率",
				"value": 4.2,
				"type": "percent"
			},
			{
				"label": "クリティカル発生率",
				"value": 6.3,
				"type": "percent"
			},
			{
				"label": "クリティカル発生率",
				"value": 8.4,
				"type": "percent"
			},
			{
				"label": "クリティカル発生率",
				"value": 10.5,
				"type": "percent"
			},
			{
				"label": "クリティカル発生率",
				"value": 12.6,
				"type": "percent"
			},
			{
				"label": "クリティカル発生率",
				"value": 14.7,
				"type": "percent"
			}
		]
	},
	"skill": [
		{
			"name": "連撃",
			"tern": 0,
			"desc": "敵単体に攻撃する。自身のスピードが高いほどダメージがUPする。自身がスピードUP状態の場合、【連撃】の代わりに【回転乱舞】を発動する。回転乱舞：敵単体に攻撃し、防御力DOWNを1ターンの間付与する。自身のスピードが高いほどダメージがUPする。(魂力1獲得)",
			"soul": {
				"soul": 1,
				"soulbern": false,
				"bern_desc": "",
				"usesoul": 0
			},
			"level": [
				{
					"label": "ダメージ",
					"value": 5,
					"type": "UP",
					"num": "percent"
				},
				{
					"label": "ダメージ",
					"value": 5,
					"type": "UP",
					"num": "percent"
				},
				{
					"label": "ダメージ",
					"value": 5,
					"type": "UP",
					"num": "percent"
				},
				{
					"label": "ダメージ",
					"value": 10,
					"type": "UP",
					"num": "percent"
				},
				{
					"label": "ダメージ",
					"value": 10,
					"type": "UP",
					"num": "percent"
				}
			],
			"material": [
				[
					{
						"name": "モラゴラ",
						"count": 1
					}
				],
				[
					{
						"name": "モラゴラ",
						"count": 1
					}
				],
				[
					{
						"name": "モラゴラ",
						"count": 1
					},
					{
						"name": "小型動力回路",
						"count": 1
					}
				],
				[
					{
						"name": "モラゴラ",
						"count": 2
					},
					{
						"name": "小型動力回路",
						"count": 3
					}
				],
				[
					{
						"name": "モラゴラゴ",
						"count": 1
					},
					{
						"name": "悪夢の仮面",
						"count": 2
					}
				]
			],
			"multiple": {
				"multiplier": "(ATK*1.599705)*(1+Speed*0.00075)",
				"modifier": "0.075% self Speed (0.00075 * Speed), Skill 2 fully upgraded increases power from 0.95 to 1.35"
			}
		},
		{
			"name": "風の心得",
			"tern": 0,
			"desc": "クリティカル発生時、自身にスピードUPを1ターンの間付与し、70%の確率でランダム強化効果を1ターンの間付与する。ランダム強化効果の付与は1ターンに1回まで発生する。ランダム強化効果：クリティカルダメージUP・効果命中率UP・回避率UP・弱体効果免疫",
			"soul": {
				"soul": 0,
				"soulbern": false,
				"bern_desc": "",
				"usesoul": 0
			},
			"level": [
				{
					"label": "効果発生率",
					"value": 5,
					"type": "UP",
					"num": "percent"
				},
				{
					"label": "効果発生率",
					"value": 5,
					"type": "UP",
					"num": "percent"
				},
				{
					"label": "効果発生率",
					"value": 5,
					"type": "UP",
					"num": "percent"
				},
				{
					"label": "効果発生率",
					"value": 5,
					"type": "UP",
					"num": "percent"
				},
				{
					"label": "効果発生率",
					"value": 10,
					"type": "UP",
					"num": "percent"
				}
			],
			"material": [
				[
					{
						"name": "モラゴラ",
						"count": 1
					}
				],
				[
					{
						"name": "モラゴラ",
						"count": 1
					}
				],
				[
					{
						"name": "モラゴラ",
						"count": 1
					},
					{
						"name": "小型動力回路",
						"count": 1
					}
				],
				[
					{
						"name": "モラゴラ",
						"count": 2
					},
					{
						"name": "小型動力回路",
						"count": 3
					}
				],
				[
					{
						"name": "モラゴラゴ",
						"count": 1
					},
					{
						"name": "悪夢の仮面",
						"count": 2
					}
				]
			],
			"multiple": {
				"multiplier": "",
				"modifier": ""
			}
		},
		{
			"name": "乱れ切り",
			"tern": 4,
			"desc": "敵単体に攻撃する。このスキルで敵を気絶させた場合、追加ターンが発生する。自身がスピードUP状態の場合、このスキルは有利属性で攻撃する。自身のスピードが高いほどダメージがUPする。(魂力2獲得)",
			"soul": {
				"soul": 2,
				"soulbern": true,
				"bern_desc": "ダメージがUPする。(魂力10消費)",
				"usesoul": 10
			},
			"level": [
				{
					"label": "ダメージ",
					"value": 5,
					"type": "UP",
					"num": "percent"
				},
				{
					"label": "ダメージ",
					"value": 5,
					"type": "UP",
					"num": "percent"
				},
				{
					"label": "スキルターン",
					"value": 1,
					"type": "減少",
					"num": "fix"
				},
				{
					"label": "ダメージ",
					"value": 10,
					"type": "UP",
					"num": "percent"
				},
				{
					"label": "ダメージ",
					"value": 10,
					"type": "UP",
					"num": "percent"
				}
			],
			"material": [
				[
					{
						"name": "モラゴラ",
						"count": 1
					}
				],
				[
					{
						"name": "モラゴラ",
						"count": 1
					}
				],
				[
					{
						"name": "モラゴラ",
						"count": 1
					},
					{
						"name": "小型動力回路",
						"count": 1
					}
				],
				[
					{
						"name": "モラゴラ",
						"count": 2
					},
					{
						"name": "小型動力回路",
						"count": 3
					}
				],
				[
					{
						"name": "モラゴラゴ",
						"count": 1
					},
					{
						"name": "悪夢の仮面",
						"count": 2
					}
				]
			],
			"multiple": {
				"multiplier": "(ATK*2.9936)*(1+Speed*0.0021) [2.2 soul burn]",
				"modifier": "0.21% self Speed (0.0021 * Speed)"
			}
		}
	],
	"name": "シダー",
	"rare": 4,
	"type": "木",
	"clazz": "アサシン",
	"thumbnail": "https://img.game8.jp/3771101/ccb4328509713f8bc62796a67bd56130.jpeg/show",
	"extention": {
		"camping": {
			"topic": [
				{
					"id": "1251",
					"name": "Complain"
				},
				{
					"id": "1241",
					"name": "Bizarre Story"
				}
			],
			"camping": {
				"1231": 0,
				"1236": 6,
				"1241": 0,
				"1246": 0,
				"1251": -3,
				"1256": 3,
				"1261": 4,
				"1266": 4,
				"1271": 1,
				"1276": -1,
				"1281": 2,
				"1286": 3,
				"1291": 4,
				"1296": 3,
				"1301": 3,
				"1306": 6,
				"1311": 1,
				"1316": 4,
				"1321": -3,
				"1326": 1,
				"1331": 3,
				"1336": 3
			}
		}
	}
}