{
	"effect": [
		{
			"skill_level": 1,
			"artifact_level": 0,
			"desc": "現在の生命力が低いほど攻撃力･スピードがUPする。最大25.0%までUPする。"
		},
		{
			"skill_level": 2,
			"artifact_level": 3,
			"desc": "現在の生命力が低いほど攻撃力･スピードがUPする。最大27.5%までUPする。"
		},
		{
			"skill_level": 3,
			"artifact_level": 6,
			"desc": "現在の生命力が低いほど攻撃力･スピードがUPする。最大30.0%までUPする。"
		},
		{
			"skill_level": 4,
			"artifact_level": 9,
			"desc": "現在の生命力が低いほど攻撃力･スピードがUPする。最大32.5%までUPする。"
		},
		{
			"skill_level": 5,
			"artifact_level": 12,
			"desc": "現在の生命力が低いほど攻撃力･スピードがUPする。最大35.0%までUPする。"
		},
		{
			"skill_level": 6,
			"artifact_level": 15,
			"desc": "現在の生命力が低いほど攻撃力･スピードがUPする。最大37.5%までUPする。"
		},
		{
			"skill_level": 7,
			"artifact_level": 18,
			"desc": "現在の生命力が低いほど攻撃力･スピードがUPする。最大40.0%までUPする。"
		},
		{
			"skill_level": 8,
			"artifact_level": 21,
			"desc": "現在の生命力が低いほど攻撃力･スピードがUPする。最大42.5%までUPする。"
		},
		{
			"skill_level": 9,
			"artifact_level": 24,
			"desc": "現在の生命力が低いほど攻撃力･スピードがUPする。最大45.0%までUPする。"
		},
		{
			"skill_level": 10,
			"artifact_level": 27,
			"desc": "現在の生命力が低いほど攻撃力･スピードがUPする。最大47.5%までUPする。"
		},
		{
			"skill_level": 11,
			"artifact_level": 30,
			"desc": "現在の生命力が低いほど攻撃力･スピードがUPする。最大50.0%までUPする。"
		}
	],
	"status": {
		"init": {
			"attack": 12,
			"health": 45
		},
		"max": {
			"attack": 156,
			"health": 585
		}
	},
	"name": "エルの拳",
	"rare": 4,
	"target": "ウォリアー",
	"thumbnail": "https://img.game8.jp/4028355/0c12bd8429534e3a164cae95a79759ee.png/show"
}