{
	"effect": [
		{
			"skill_level": 1,
			"artifact_level": 0,
			"desc": "敵単体に攻撃した時、対象が木属性の場合、アクションゲージを5.0%DOWNさせる。"
		},
		{
			"skill_level": 2,
			"artifact_level": 3,
			"desc": "敵単体に攻撃した時、対象が木属性の場合、アクションゲージを5.5%DOWNさせる。"
		},
		{
			"skill_level": 3,
			"artifact_level": 6,
			"desc": "敵単体に攻撃した時、対象が木属性の場合、アクションゲージを6.0%DOWNさせる。"
		},
		{
			"skill_level": 4,
			"artifact_level": 9,
			"desc": "敵単体に攻撃した時、対象が木属性の場合、アクションゲージを6.5%DOWNさせる。"
		},
		{
			"skill_level": 5,
			"artifact_level": 12,
			"desc": "敵単体に攻撃した時、対象が木属性の場合、アクションゲージを7.0%DOWNさせる。"
		},
		{
			"skill_level": 6,
			"artifact_level": 15,
			"desc": "敵単体に攻撃した時、対象が木属性の場合、アクションゲージを7.5%DOWNさせる。"
		},
		{
			"skill_level": 7,
			"artifact_level": 18,
			"desc": "敵単体に攻撃した時、対象が木属性の場合、アクションゲージを8.0%DOWNさせる。"
		},
		{
			"skill_level": 8,
			"artifact_level": 21,
			"desc": "敵単体に攻撃した時、対象が木属性の場合、アクションゲージを8.5%DOWNさせる。"
		},
		{
			"skill_level": 9,
			"artifact_level": 24,
			"desc": "敵単体に攻撃した時、対象が木属性の場合、アクションゲージを9.0%DOWNさせる。"
		},
		{
			"skill_level": 10,
			"artifact_level": 27,
			"desc": "敵単体に攻撃した時、対象が木属性の場合、アクションゲージを9.5%DOWNさせる。"
		},
		{
			"skill_level": 11,
			"artifact_level": 30,
			"desc": "敵単体に攻撃した時、対象が木属性の場合、アクションゲージを10.0%DOWNさせる。"
		}
	],
	"status": {
		"init": {
			"attack": 18,
			"health": 27
		},
		"max": {
			"attack": 234,
			"health": 351
		}
	},
	"thumbnail": "https://img.game8.jp/4921356/24f397571415fb6a5326a99af5edb69f.png/show",
	"name": "サンタ・ムエルテ",
	"rare": 4,
	"target": "アサシン"
}