{
	"effect": [
		{
			"skill_level": 1,
			"artifact_level": 0,
			"desc": "敵単体に攻撃した後、自身の攻撃力が5.0%UPし、対象に15.0%の確率で沈黙を1ターンの間付与する。攻撃力UP効果は、最大3回まで累積する。"
		},
		{
			"skill_level": 2,
			"artifact_level": 3,
			"desc": "敵単体に攻撃した後、自身の攻撃力が5.5%UPし、対象に16.5%の確率で沈黙を1ターンの間付与する。攻撃力UP効果は、最大3回まで累積する。"
		},
		{
			"skill_level": 3,
			"artifact_level": 6,
			"desc": "敵単体に攻撃した後、自身の攻撃力が6.0%UPし、対象に18.0%の確率で沈黙を1ターンの間付与する。攻撃力UP効果は、最大3回まで累積する。"
		},
		{
			"skill_level": 4,
			"artifact_level": 9,
			"desc": "敵単体に攻撃した後、自身の攻撃力が6.5%UPし、対象に19.5%の確率で沈黙を1ターンの間付与する。攻撃力UP効果は、最大3回まで累積する。"
		},
		{
			"skill_level": 5,
			"artifact_level": 12,
			"desc": "敵単体に攻撃した後、自身の攻撃力が7.0%UPし、対象に21.0%の確率で沈黙を1ターンの間付与する。攻撃力UP効果は、最大3回まで累積する。"
		},
		{
			"skill_level": 6,
			"artifact_level": 15,
			"desc": "敵単体に攻撃した後、自身の攻撃力が7.5%UPし、対象に22.5%の確率で沈黙を1ターンの間付与する。攻撃力UP効果は、最大3回まで累積する。"
		},
		{
			"skill_level": 7,
			"artifact_level": 18,
			"desc": "敵単体に攻撃した後、自身の攻撃力が8.0%UPし、対象に24.0%の確率で沈黙を1ターンの間付与する。攻撃力UP効果は、最大3回まで累積する。"
		},
		{
			"skill_level": 8,
			"artifact_level": 21,
			"desc": "敵単体に攻撃した後、自身の攻撃力が8.5%UPし、対象に25.5%の確率で沈黙を1ターンの間付与する。攻撃力UP効果は、最大3回まで累積する。"
		},
		{
			"skill_level": 9,
			"artifact_level": 24,
			"desc": "敵単体に攻撃した後、自身の攻撃力が9.0%UPし、対象に27.0%の確率で沈黙を1ターンの間付与する。攻撃力UP効果は、最大3回まで累積する。"
		},
		{
			"skill_level": 10,
			"artifact_level": 27,
			"desc": "敵単体に攻撃した後、自身の攻撃力が9.5%UPし、対象に28.5%の確率で沈黙を1ターンの間付与する。攻撃力UP効果は、最大3回まで累積する。"
		},
		{
			"skill_level": 11,
			"artifact_level": 30,
			"desc": "敵単体に攻撃した後、自身の攻撃力が10.0%UPし、対象に30.0%の確率で沈黙を1ターンの間付与する。攻撃力UP効果は、最大3回まで累積する。"
		}
	],
	"status": {
		"init": {
			"attack": 21,
			"health": 32
		},
		"max": {
			"attack": 273,
			"health": 416
		}
	},
	"thumbnail": "https://img.game8.jp/5466625/02c54e12d1ce7bc5f4317798255651cf.png/show",
	"name": "両人剣デクレッシェンド",
	"rare": 5,
	"target": "アサシン"
}