{
	"effect": [
		{
			"skill_level": 1,
			"artifact_level": 0,
			"desc": "攻撃以外のスキルを使用した時、自身の攻撃力が7.5%・スピードが5.0%UPする。最大3回まで累積する。"
		},
		{
			"skill_level": 2,
			"artifact_level": 3,
			"desc": "攻撃以外のスキルを使用した時、自身の攻撃力が8.3%・スピードが5.5%UPする。最大3回まで累積する。"
		},
		{
			"skill_level": 3,
			"artifact_level": 6,
			"desc": "攻撃以外のスキルを使用した時、自身の攻撃力が9.0%・スピードが6.0%UPする。最大3回まで累積する。"
		},
		{
			"skill_level": 4,
			"artifact_level": 9,
			"desc": "攻撃以外のスキルを使用した時、自身の攻撃力が9.8%・スピードが6.5%UPする。最大3回まで累積する。"
		},
		{
			"skill_level": 5,
			"artifact_level": 12,
			"desc": "攻撃以外のスキルを使用した時、自身の攻撃力が10.5%・スピードが7.0%UPする。最大3回まで累積する。"
		},
		{
			"skill_level": 6,
			"artifact_level": 15,
			"desc": "攻撃以外のスキルを使用した時、自身の攻撃力が11.3%・スピードが7.5%UPする。最大3回まで累積する。"
		},
		{
			"skill_level": 7,
			"artifact_level": 18,
			"desc": "攻撃以外のスキルを使用した時、自身の攻撃力が12.0%・スピードが8.0%UPする。最大3回まで累積する。"
		},
		{
			"skill_level": 8,
			"artifact_level": 21,
			"desc": "攻撃以外のスキルを使用した時、自身の攻撃力が12.8%・スピードが8.5%UPする。最大3回まで累積する。"
		},
		{
			"skill_level": 9,
			"artifact_level": 24,
			"desc": "攻撃以外のスキルを使用した時、自身の攻撃力が13.5%・スピードが9.0%UPする。最大3回まで累積する。"
		},
		{
			"skill_level": 10,
			"artifact_level": 27,
			"desc": "攻撃以外のスキルを使用した時、自身の攻撃力が14.3%・スピードが9.5%UPする。最大3回まで累積する。"
		},
		{
			"skill_level": 11,
			"artifact_level": 30,
			"desc": "攻撃以外のスキルを使用した時、自身の攻撃力が15.0%・スピードが10.0%UPする。最大3回まで累積する。"
		}
	],
	"status": {
		"init": {
			"attack": 21,
			"health": 32
		},
		"max": {
			"attack": 273,
			"health": 416
		}
	},
	"name": "天命の金貨",
	"rare": 5,
	"target": "ウォリアー",
	"thumbnail": "https://img.game8.jp/4028289/fc438ea7b8047a2062a199927555e682.png/show"
}